{
  "db_name": "PostgreSQL",
  "query": "SELECT id, name, manufacturer, product_url AS \"product_url: _\", value, created_at, created_by\n            FROM asset_types;",
  "describe": {
    "columns": [
      {
        "ordinal": 0,
        "name": "id",
        "type_info": "Uuid",
        "origin": {
          "Table": {
            "table": "asset_types",
            "name": "id"
          }
        }
      },
      {
        "ordinal": 1,
        "name": "name",
        "type_info": "Text",
        "origin": {
          "Table": {
            "table": "asset_types",
            "name": "name"
          }
        }
      },
      {
        "ordinal": 2,
        "name": "manufacturer",
        "type_info": "Uuid",
        "origin": {
          "Table": {
            "table": "asset_types",
            "name": "manufacturer"
          }
        }
      },
      {
        "ordinal": 3,
        "name": "product_url: _",
        "type_info": "Text",
        "origin": {
          "Table": {
            "table": "asset_types",
            "name": "product_url"
          }
        }
      },
      {
        "ordinal": 4,
        "name": "value",
        "type_info": "Numeric",
        "origin": {
          "Table": {
            "table": "asset_types",
            "name": "value"
          }
        }
      },
      {
        "ordinal": 5,
        "name": "created_at",
        "type_info": "Timestamptz",
        "origin": {
          "Table": {
            "table": "asset_types",
            "name": "created_at"
          }
        }
      },
      {
        "ordinal": 6,
        "name": "created_by",
        "type_info": "Uuid",
        "origin": {
          "Table": {
            "table": "asset_types",
            "name": "created_by"
          }
        }
      }
    ],
    "parameters": {
      "Left": []
    },
    "nullable": [
      false,
      false,
      false,
      true,
      true,
      false,
      false
    ]
  },
  "hash": "d3633265a3ff785f6106d8217f1bb17dcd831f911544224290aafe833f8365c7"
}
